{
  "version": "tree-0.1",
  "tree": {
    "id": "App",
    "path": "",
    "children": {
      "costhub-auth-prod": {
        "id": "costhub-auth-prod",
        "path": "costhub-auth-prod",
        "children": {
          "CostHubUserPool": {
            "id": "CostHubUserPool",
            "path": "costhub-auth-prod/CostHubUserPool",
            "children": {
              "Resource": {
                "id": "Resource",
                "path": "costhub-auth-prod/CostHubUserPool/Resource",
                "attributes": {
                  "aws:cdk:cloudformation:type": "AWS::Cognito::UserPool",
                  "aws:cdk:cloudformation:props": {
                    "accountRecoverySetting": {
                      "recoveryMechanisms": [
                        {
                          "name": "verified_email",
                          "priority": 1
                        }
                      ]
                    },
                    "adminCreateUserConfig": {
                      "allowAdminCreateUserOnly": true
                    },
                    "autoVerifiedAttributes": [
                      "email"
                    ],
                    "emailVerificationMessage": "The verification code to your new account is {####}",
                    "emailVerificationSubject": "Verify your new account",
                    "policies": {
                      "passwordPolicy": {
                        "minimumLength": 8,
                        "requireLowercase": true,
                        "requireUppercase": true,
                        "requireNumbers": true,
                        "requireSymbols": false
                      }
                    },
                    "smsVerificationMessage": "The verification code to your new account is {####}",
                    "usernameAttributes": [
                      "email"
                    ],
                    "userPoolName": "costhub-users",
                    "verificationMessageTemplate": {
                      "defaultEmailOption": "CONFIRM_WITH_CODE",
                      "emailMessage": "The verification code to your new account is {####}",
                      "emailSubject": "Verify your new account",
                      "smsMessage": "The verification code to your new account is {####}"
                    }
                  }
                },
                "constructInfo": {
                  "fqn": "aws-cdk-lib.aws_cognito.CfnUserPool",
                  "version": "2.122.0"
                }
              }
            },
            "constructInfo": {
              "fqn": "aws-cdk-lib.aws_cognito.UserPool",
              "version": "2.122.0"
            }
          },
          "CostHubUserPoolClient": {
            "id": "CostHubUserPoolClient",
            "path": "costhub-auth-prod/CostHubUserPoolClient",
            "children": {
              "Resource": {
                "id": "Resource",
                "path": "costhub-auth-prod/CostHubUserPoolClient/Resource",
                "attributes": {
                  "aws:cdk:cloudformation:type": "AWS::Cognito::UserPoolClient",
                  "aws:cdk:cloudformation:props": {
                    "allowedOAuthFlows": [
                      "implicit",
                      "code"
                    ],
                    "allowedOAuthFlowsUserPoolClient": true,
                    "allowedOAuthScopes": [
                      "email",
                      "openid",
                      "profile"
                    ],
                    "callbackUrLs": [
                      "https://costhub.4bfast.com.br/auth/callback",
                      "http://localhost:3000/auth/callback"
                    ],
                    "clientName": "costhub-web-client",
                    "explicitAuthFlows": [
                      "ALLOW_USER_PASSWORD_AUTH",
                      "ALLOW_USER_SRP_AUTH",
                      "ALLOW_REFRESH_TOKEN_AUTH"
                    ],
                    "logoutUrLs": [
                      "https://costhub.4bfast.com.br/auth/logout",
                      "http://localhost:3000/auth/logout"
                    ],
                    "supportedIdentityProviders": [
                      "COGNITO"
                    ],
                    "userPoolId": {
                      "Ref": "CostHubUserPool4652F8DE"
                    }
                  }
                },
                "constructInfo": {
                  "fqn": "aws-cdk-lib.aws_cognito.CfnUserPoolClient",
                  "version": "2.122.0"
                }
              }
            },
            "constructInfo": {
              "fqn": "aws-cdk-lib.aws_cognito.UserPoolClient",
              "version": "2.122.0"
            }
          },
          "CostHubUserPoolDomain": {
            "id": "CostHubUserPoolDomain",
            "path": "costhub-auth-prod/CostHubUserPoolDomain",
            "children": {
              "Resource": {
                "id": "Resource",
                "path": "costhub-auth-prod/CostHubUserPoolDomain/Resource",
                "attributes": {
                  "aws:cdk:cloudformation:type": "AWS::Cognito::UserPoolDomain",
                  "aws:cdk:cloudformation:props": {
                    "domain": "costhub-auth-4bfast-com-br",
                    "userPoolId": {
                      "Ref": "CostHubUserPool4652F8DE"
                    }
                  }
                },
                "constructInfo": {
                  "fqn": "aws-cdk-lib.aws_cognito.CfnUserPoolDomain",
                  "version": "2.122.0"
                }
              }
            },
            "constructInfo": {
              "fqn": "aws-cdk-lib.aws_cognito.UserPoolDomain",
              "version": "2.122.0"
            }
          },
          "UserPoolId": {
            "id": "UserPoolId",
            "path": "costhub-auth-prod/UserPoolId",
            "constructInfo": {
              "fqn": "aws-cdk-lib.CfnOutput",
              "version": "2.122.0"
            }
          },
          "UserPoolClientId": {
            "id": "UserPoolClientId",
            "path": "costhub-auth-prod/UserPoolClientId",
            "constructInfo": {
              "fqn": "aws-cdk-lib.CfnOutput",
              "version": "2.122.0"
            }
          },
          "CognitoDomainUrl": {
            "id": "CognitoDomainUrl",
            "path": "costhub-auth-prod/CognitoDomainUrl",
            "constructInfo": {
              "fqn": "aws-cdk-lib.CfnOutput",
              "version": "2.122.0"
            }
          },
          "CDKMetadata": {
            "id": "CDKMetadata",
            "path": "costhub-auth-prod/CDKMetadata",
            "children": {
              "Default": {
                "id": "Default",
                "path": "costhub-auth-prod/CDKMetadata/Default",
                "constructInfo": {
                  "fqn": "aws-cdk-lib.CfnResource",
                  "version": "2.122.0"
                }
              }
            },
            "constructInfo": {
              "fqn": "constructs.Construct",
              "version": "10.4.2"
            }
          },
          "BootstrapVersion": {
            "id": "BootstrapVersion",
            "path": "costhub-auth-prod/BootstrapVersion",
            "constructInfo": {
              "fqn": "aws-cdk-lib.CfnParameter",
              "version": "2.122.0"
            }
          },
          "CheckBootstrapVersion": {
            "id": "CheckBootstrapVersion",
            "path": "costhub-auth-prod/CheckBootstrapVersion",
            "constructInfo": {
              "fqn": "aws-cdk-lib.CfnRule",
              "version": "2.122.0"
            }
          }
        },
        "constructInfo": {
          "fqn": "aws-cdk-lib.Stack",
          "version": "2.122.0"
        }
      },
      "costhub-frontend-api-prod": {
        "id": "costhub-frontend-api-prod",
        "path": "costhub-frontend-api-prod",
        "children": {
          "APIHandler": {
            "id": "APIHandler",
            "path": "costhub-frontend-api-prod/APIHandler",
            "children": {
              "ServiceRole": {
                "id": "ServiceRole",
                "path": "costhub-frontend-api-prod/APIHandler/ServiceRole",
                "children": {
                  "ImportServiceRole": {
                    "id": "ImportServiceRole",
                    "path": "costhub-frontend-api-prod/APIHandler/ServiceRole/ImportServiceRole",
                    "constructInfo": {
                      "fqn": "aws-cdk-lib.Resource",
                      "version": "2.122.0"
                    }
                  },
                  "Resource": {
                    "id": "Resource",
                    "path": "costhub-frontend-api-prod/APIHandler/ServiceRole/Resource",
                    "attributes": {
                      "aws:cdk:cloudformation:type": "AWS::IAM::Role",
                      "aws:cdk:cloudformation:props": {
                        "assumeRolePolicyDocument": {
                          "Statement": [
                            {
                              "Action": "sts:AssumeRole",
                              "Effect": "Allow",
                              "Principal": {
                                "Service": "lambda.amazonaws.com"
                              }
                            }
                          ],
                          "Version": "2012-10-17"
                        },
                        "managedPolicyArns": [
                          {
                            "Fn::Join": [
                              "",
                              [
                                "arn:",
                                {
                                  "Ref": "AWS::Partition"
                                },
                                ":iam::aws:policy/service-role/AWSLambdaBasicExecutionRole"
                              ]
                            ]
                          }
                        ]
                      }
                    },
                    "constructInfo": {
                      "fqn": "aws-cdk-lib.aws_iam.CfnRole",
                      "version": "2.122.0"
                    }
                  }
                },
                "constructInfo": {
                  "fqn": "aws-cdk-lib.aws_iam.Role",
                  "version": "2.122.0"
                }
              },
              "Code": {
                "id": "Code",
                "path": "costhub-frontend-api-prod/APIHandler/Code",
                "children": {
                  "Stage": {
                    "id": "Stage",
                    "path": "costhub-frontend-api-prod/APIHandler/Code/Stage",
                    "constructInfo": {
                      "fqn": "aws-cdk-lib.AssetStaging",
                      "version": "2.122.0"
                    }
                  },
                  "AssetBucket": {
                    "id": "AssetBucket",
                    "path": "costhub-frontend-api-prod/APIHandler/Code/AssetBucket",
                    "constructInfo": {
                      "fqn": "aws-cdk-lib.aws_s3.BucketBase",
                      "version": "2.122.0"
                    }
                  }
                },
                "constructInfo": {
                  "fqn": "aws-cdk-lib.aws_s3_assets.Asset",
                  "version": "2.122.0"
                }
              },
              "Resource": {
                "id": "Resource",
                "path": "costhub-frontend-api-prod/APIHandler/Resource",
                "attributes": {
                  "aws:cdk:cloudformation:type": "AWS::Lambda::Function",
                  "aws:cdk:cloudformation:props": {
                    "code": {
                      "s3Bucket": "cdk-hnb659fds-assets-008195334540-us-east-1",
                      "s3Key": "bcaf55e1d38eac032e49b5482f186962c16b2105a8943f7e624bc901ba524288.zip"
                    },
                    "description": "API Gateway Handler for Frontend Integration",
                    "environment": {
                      "variables": {
                        "CORS_ALLOWED_ORIGINS": "https://costhub.4bfast.com.br,https://www.costhub.4bfast.com.br",
                        "LOG_LEVEL": "INFO"
                      }
                    },
                    "handler": "simple_handlers.api_gateway_handler_simple.lambda_handler",
                    "memorySize": 512,
                    "role": {
                      "Fn::GetAtt": [
                        "APIHandlerServiceRole41BB65E0",
                        "Arn"
                      ]
                    },
                    "runtime": "python3.11",
                    "timeout": 30
                  }
                },
                "constructInfo": {
                  "fqn": "aws-cdk-lib.aws_lambda.CfnFunction",
                  "version": "2.122.0"
                }
              }
            },
            "constructInfo": {
              "fqn": "aws-cdk-lib.aws_lambda.Function",
              "version": "2.122.0"
            }
          },
          "UserPool": {
            "id": "UserPool",
            "path": "costhub-frontend-api-prod/UserPool",
            "constructInfo": {
              "fqn": "aws-cdk-lib.Resource",
              "version": "2.122.0"
            }
          },
          "CognitoAuthorizer": {
            "id": "CognitoAuthorizer",
            "path": "costhub-frontend-api-prod/CognitoAuthorizer",
            "children": {
              "Resource": {
                "id": "Resource",
                "path": "costhub-frontend-api-prod/CognitoAuthorizer/Resource",
                "attributes": {
                  "aws:cdk:cloudformation:type": "AWS::ApiGateway::Authorizer",
                  "aws:cdk:cloudformation:props": {
                    "identitySource": "method.request.header.Authorization",
                    "name": "costhubfrontendapiprodCognitoAuthorizerAD28A7A4",
                    "providerArns": [
                      {
                        "Fn::Join": [
                          "",
                          [
                            "arn:",
                            {
                              "Ref": "AWS::Partition"
                            },
                            ":cognito-idp:us-east-1:008195334540:userpool/us-east-1_94OYkzcSO"
                          ]
                        ]
                      }
                    ],
                    "restApiId": {
                      "Ref": "FrontendAPI00E92687"
                    },
                    "type": "COGNITO_USER_POOLS"
                  }
                },
                "constructInfo": {
                  "fqn": "aws-cdk-lib.aws_apigateway.CfnAuthorizer",
                  "version": "2.122.0"
                }
              }
            },
            "constructInfo": {
              "fqn": "aws-cdk-lib.aws_apigateway.CognitoUserPoolsAuthorizer",
              "version": "2.122.0"
            }
          },
          "FrontendAPI": {
            "id": "FrontendAPI",
            "path": "costhub-frontend-api-prod/FrontendAPI",
            "children": {
              "Resource": {
                "id": "Resource",
                "path": "costhub-frontend-api-prod/FrontendAPI/Resource",
                "attributes": {
                  "aws:cdk:cloudformation:type": "AWS::ApiGateway::RestApi",
                  "aws:cdk:cloudformation:props": {
                    "description": "CostHub Frontend API with Authentication",
                    "name": "costhub-frontend-api"
                  }
                },
                "constructInfo": {
                  "fqn": "aws-cdk-lib.aws_apigateway.CfnRestApi",
                  "version": "2.122.0"
                }
              },
              "CloudWatchRole": {
                "id": "CloudWatchRole",
                "path": "costhub-frontend-api-prod/FrontendAPI/CloudWatchRole",
                "children": {
                  "ImportCloudWatchRole": {
                    "id": "ImportCloudWatchRole",
                    "path": "costhub-frontend-api-prod/FrontendAPI/CloudWatchRole/ImportCloudWatchRole",
                    "constructInfo": {
                      "fqn": "aws-cdk-lib.Resource",
                      "version": "2.122.0"
                    }
                  },
                  "Resource": {
                    "id": "Resource",
                    "path": "costhub-frontend-api-prod/FrontendAPI/CloudWatchRole/Resource",
                    "attributes": {
                      "aws:cdk:cloudformation:type": "AWS::IAM::Role",
                      "aws:cdk:cloudformation:props": {
                        "assumeRolePolicyDocument": {
                          "Statement": [
                            {
                              "Action": "sts:AssumeRole",
                              "Effect": "Allow",
                              "Principal": {
                                "Service": "apigateway.amazonaws.com"
                              }
                            }
                          ],
                          "Version": "2012-10-17"
                        },
                        "managedPolicyArns": [
                          {
                            "Fn::Join": [
                              "",
                              [
                                "arn:",
                                {
                                  "Ref": "AWS::Partition"
                                },
                                ":iam::aws:policy/service-role/AmazonAPIGatewayPushToCloudWatchLogs"
                              ]
                            ]
                          }
                        ]
                      }
                    },
                    "constructInfo": {
                      "fqn": "aws-cdk-lib.aws_iam.CfnRole",
                      "version": "2.122.0"
                    }
                  }
                },
                "constructInfo": {
                  "fqn": "aws-cdk-lib.aws_iam.Role",
                  "version": "2.122.0"
                }
              },
              "Account": {
                "id": "Account",
                "path": "costhub-frontend-api-prod/FrontendAPI/Account",
                "attributes": {
                  "aws:cdk:cloudformation:type": "AWS::ApiGateway::Account",
                  "aws:cdk:cloudformation:props": {
                    "cloudWatchRoleArn": {
                      "Fn::GetAtt": [
                        "FrontendAPICloudWatchRoleDCFD42BB",
                        "Arn"
                      ]
                    }
                  }
                },
                "constructInfo": {
                  "fqn": "aws-cdk-lib.aws_apigateway.CfnAccount",
                  "version": "2.122.0"
                }
              },
              "Deployment": {
                "id": "Deployment",
                "path": "costhub-frontend-api-prod/FrontendAPI/Deployment",
                "children": {
                  "Resource": {
                    "id": "Resource",
                    "path": "costhub-frontend-api-prod/FrontendAPI/Deployment/Resource",
                    "attributes": {
                      "aws:cdk:cloudformation:type": "AWS::ApiGateway::Deployment",
                      "aws:cdk:cloudformation:props": {
                        "description": "CostHub Frontend API with Authentication",
                        "restApiId": {
                          "Ref": "FrontendAPI00E92687"
                        }
                      }
                    },
                    "constructInfo": {
                      "fqn": "aws-cdk-lib.aws_apigateway.CfnDeployment",
                      "version": "2.122.0"
                    }
                  }
                },
                "constructInfo": {
                  "fqn": "aws-cdk-lib.aws_apigateway.Deployment",
                  "version": "2.122.0"
                }
              },
              "DeploymentStage.prod": {
                "id": "DeploymentStage.prod",
                "path": "costhub-frontend-api-prod/FrontendAPI/DeploymentStage.prod",
                "children": {
                  "Resource": {
                    "id": "Resource",
                    "path": "costhub-frontend-api-prod/FrontendAPI/DeploymentStage.prod/Resource",
                    "attributes": {
                      "aws:cdk:cloudformation:type": "AWS::ApiGateway::Stage",
                      "aws:cdk:cloudformation:props": {
                        "deploymentId": {
                          "Ref": "FrontendAPIDeploymentBE18F28Eef5465b99bee71d96a4e41c59a1b98af"
                        },
                        "methodSettings": [
                          {
                            "httpMethod": "*",
                            "resourcePath": "/*",
                            "dataTraceEnabled": false,
                            "throttlingBurstLimit": 2000,
                            "throttlingRateLimit": 1000
                          }
                        ],
                        "restApiId": {
                          "Ref": "FrontendAPI00E92687"
                        },
                        "stageName": "prod"
                      }
                    },
                    "constructInfo": {
                      "fqn": "aws-cdk-lib.aws_apigateway.CfnStage",
                      "version": "2.122.0"
                    }
                  }
                },
                "constructInfo": {
                  "fqn": "aws-cdk-lib.aws_apigateway.Stage",
                  "version": "2.122.0"
                }
              },
              "Endpoint": {
                "id": "Endpoint",
                "path": "costhub-frontend-api-prod/FrontendAPI/Endpoint",
                "constructInfo": {
                  "fqn": "aws-cdk-lib.CfnOutput",
                  "version": "2.122.0"
                }
              },
              "Default": {
                "id": "Default",
                "path": "costhub-frontend-api-prod/FrontendAPI/Default",
                "children": {
                  "OPTIONS": {
                    "id": "OPTIONS",
                    "path": "costhub-frontend-api-prod/FrontendAPI/Default/OPTIONS",
                    "children": {
                      "Resource": {
                        "id": "Resource",
                        "path": "costhub-frontend-api-prod/FrontendAPI/Default/OPTIONS/Resource",
                        "attributes": {
                          "aws:cdk:cloudformation:type": "AWS::ApiGateway::Method",
                          "aws:cdk:cloudformation:props": {
                            "apiKeyRequired": false,
                            "authorizationType": "NONE",
                            "httpMethod": "OPTIONS",
                            "integration": {
                              "type": "MOCK",
                              "requestTemplates": {
                                "application/json": "{ statusCode: 200 }"
                              },
                              "integrationResponses": [
                                {
                                  "statusCode": "204",
                                  "responseParameters": {
                                    "method.response.header.Access-Control-Allow-Headers": "'Content-Type,Authorization,X-Requested-With,x-request-id,X-Amz-Date,X-Api-Key,X-Amz-Security-Token'",
                                    "method.response.header.Access-Control-Allow-Origin": "'https://costhub.4bfast.com.br'",
                                    "method.response.header.Vary": "'Origin'",
                                    "method.response.header.Access-Control-Allow-Methods": "'GET,POST,PUT,DELETE,OPTIONS'",
                                    "method.response.header.Access-Control-Allow-Credentials": "'true'"
                                  },
                                  "responseTemplates": {
                                    "application/json": "#set($origin = $input.params().header.get(\"Origin\"))\n#if($origin == \"\")\n  #set($origin = $input.params().header.get(\"origin\"))\n#end\n#if($origin == \"https://www.costhub.4bfast.com.br\")\n  #set($context.responseOverride.header.Access-Control-Allow-Origin = $origin)\n#end"
                                  }
                                }
                              ]
                            },
                            "methodResponses": [
                              {
                                "statusCode": "204",
                                "responseParameters": {
                                  "method.response.header.Access-Control-Allow-Headers": true,
                                  "method.response.header.Access-Control-Allow-Origin": true,
                                  "method.response.header.Vary": true,
                                  "method.response.header.Access-Control-Allow-Methods": true,
                                  "method.response.header.Access-Control-Allow-Credentials": true
                                }
                              }
                            ],
                            "resourceId": {
                              "Fn::GetAtt": [
                                "FrontendAPI00E92687",
                                "RootResourceId"
                              ]
                            },
                            "restApiId": {
                              "Ref": "FrontendAPI00E92687"
                            }
                          }
                        },
                        "constructInfo": {
                          "fqn": "aws-cdk-lib.aws_apigateway.CfnMethod",
                          "version": "2.122.0"
                        }
                      }
                    },
                    "constructInfo": {
                      "fqn": "aws-cdk-lib.aws_apigateway.Method",
                      "version": "2.122.0"
                    }
                  },
                  "api": {
                    "id": "api",
                    "path": "costhub-frontend-api-prod/FrontendAPI/Default/api",
                    "children": {
                      "Resource": {
                        "id": "Resource",
                        "path": "costhub-frontend-api-prod/FrontendAPI/Default/api/Resource",
                        "attributes": {
                          "aws:cdk:cloudformation:type": "AWS::ApiGateway::Resource",
                          "aws:cdk:cloudformation:props": {
                            "parentId": {
                              "Fn::GetAtt": [
                                "FrontendAPI00E92687",
                                "RootResourceId"
                              ]
                            },
                            "pathPart": "api",
                            "restApiId": {
                              "Ref": "FrontendAPI00E92687"
                            }
                          }
                        },
                        "constructInfo": {
                          "fqn": "aws-cdk-lib.aws_apigateway.CfnResource",
                          "version": "2.122.0"
                        }
                      },
                      "OPTIONS": {
                        "id": "OPTIONS",
                        "path": "costhub-frontend-api-prod/FrontendAPI/Default/api/OPTIONS",
                        "children": {
                          "Resource": {
                            "id": "Resource",
                            "path": "costhub-frontend-api-prod/FrontendAPI/Default/api/OPTIONS/Resource",
                            "attributes": {
                              "aws:cdk:cloudformation:type": "AWS::ApiGateway::Method",
                              "aws:cdk:cloudformation:props": {
                                "apiKeyRequired": false,
                                "authorizationType": "NONE",
                                "httpMethod": "OPTIONS",
                                "integration": {
                                  "type": "MOCK",
                                  "requestTemplates": {
                                    "application/json": "{ statusCode: 200 }"
                                  },
                                  "integrationResponses": [
                                    {
                                      "statusCode": "204",
                                      "responseParameters": {
                                        "method.response.header.Access-Control-Allow-Headers": "'Content-Type,Authorization,X-Requested-With,x-request-id,X-Amz-Date,X-Api-Key,X-Amz-Security-Token'",
                                        "method.response.header.Access-Control-Allow-Origin": "'https://costhub.4bfast.com.br'",
                                        "method.response.header.Vary": "'Origin'",
                                        "method.response.header.Access-Control-Allow-Methods": "'GET,POST,PUT,DELETE,OPTIONS'",
                                        "method.response.header.Access-Control-Allow-Credentials": "'true'"
                                      },
                                      "responseTemplates": {
                                        "application/json": "#set($origin = $input.params().header.get(\"Origin\"))\n#if($origin == \"\")\n  #set($origin = $input.params().header.get(\"origin\"))\n#end\n#if($origin == \"https://www.costhub.4bfast.com.br\")\n  #set($context.responseOverride.header.Access-Control-Allow-Origin = $origin)\n#end"
                                      }
                                    }
                                  ]
                                },
                                "methodResponses": [
                                  {
                                    "statusCode": "204",
                                    "responseParameters": {
                                      "method.response.header.Access-Control-Allow-Headers": true,
                                      "method.response.header.Access-Control-Allow-Origin": true,
                                      "method.response.header.Vary": true,
                                      "method.response.header.Access-Control-Allow-Methods": true,
                                      "method.response.header.Access-Control-Allow-Credentials": true
                                    }
                                  }
                                ],
                                "resourceId": {
                                  "Ref": "FrontendAPIapi928960A9"
                                },
                                "restApiId": {
                                  "Ref": "FrontendAPI00E92687"
                                }
                              }
                            },
                            "constructInfo": {
                              "fqn": "aws-cdk-lib.aws_apigateway.CfnMethod",
                              "version": "2.122.0"
                            }
                          }
                        },
                        "constructInfo": {
                          "fqn": "aws-cdk-lib.aws_apigateway.Method",
                          "version": "2.122.0"
                        }
                      },
                      "v1": {
                        "id": "v1",
                        "path": "costhub-frontend-api-prod/FrontendAPI/Default/api/v1",
                        "children": {
                          "Resource": {
                            "id": "Resource",
                            "path": "costhub-frontend-api-prod/FrontendAPI/Default/api/v1/Resource",
                            "attributes": {
                              "aws:cdk:cloudformation:type": "AWS::ApiGateway::Resource",
                              "aws:cdk:cloudformation:props": {
                                "parentId": {
                                  "Ref": "FrontendAPIapi928960A9"
                                },
                                "pathPart": "v1",
                                "restApiId": {
                                  "Ref": "FrontendAPI00E92687"
                                }
                              }
                            },
                            "constructInfo": {
                              "fqn": "aws-cdk-lib.aws_apigateway.CfnResource",
                              "version": "2.122.0"
                            }
                          },
                          "OPTIONS": {
                            "id": "OPTIONS",
                            "path": "costhub-frontend-api-prod/FrontendAPI/Default/api/v1/OPTIONS",
                            "children": {
                              "Resource": {
                                "id": "Resource",
                                "path": "costhub-frontend-api-prod/FrontendAPI/Default/api/v1/OPTIONS/Resource",
                                "attributes": {
                                  "aws:cdk:cloudformation:type": "AWS::ApiGateway::Method",
                                  "aws:cdk:cloudformation:props": {
                                    "apiKeyRequired": false,
                                    "authorizationType": "NONE",
                                    "httpMethod": "OPTIONS",
                                    "integration": {
                                      "type": "MOCK",
                                      "requestTemplates": {
                                        "application/json": "{ statusCode: 200 }"
                                      },
                                      "integrationResponses": [
                                        {
                                          "statusCode": "204",
                                          "responseParameters": {
                                            "method.response.header.Access-Control-Allow-Headers": "'Content-Type,Authorization,X-Requested-With,x-request-id,X-Amz-Date,X-Api-Key,X-Amz-Security-Token'",
                                            "method.response.header.Access-Control-Allow-Origin": "'https://costhub.4bfast.com.br'",
                                            "method.response.header.Vary": "'Origin'",
                                            "method.response.header.Access-Control-Allow-Methods": "'GET,POST,PUT,DELETE,OPTIONS'",
                                            "method.response.header.Access-Control-Allow-Credentials": "'true'"
                                          },
                                          "responseTemplates": {
                                            "application/json": "#set($origin = $input.params().header.get(\"Origin\"))\n#if($origin == \"\")\n  #set($origin = $input.params().header.get(\"origin\"))\n#end\n#if($origin == \"https://www.costhub.4bfast.com.br\")\n  #set($context.responseOverride.header.Access-Control-Allow-Origin = $origin)\n#end"
                                          }
                                        }
                                      ]
                                    },
                                    "methodResponses": [
                                      {
                                        "statusCode": "204",
                                        "responseParameters": {
                                          "method.response.header.Access-Control-Allow-Headers": true,
                                          "method.response.header.Access-Control-Allow-Origin": true,
                                          "method.response.header.Vary": true,
                                          "method.response.header.Access-Control-Allow-Methods": true,
                                          "method.response.header.Access-Control-Allow-Credentials": true
                                        }
                                      }
                                    ],
                                    "resourceId": {
                                      "Ref": "FrontendAPIapiv10C580F49"
                                    },
                                    "restApiId": {
                                      "Ref": "FrontendAPI00E92687"
                                    }
                                  }
                                },
                                "constructInfo": {
                                  "fqn": "aws-cdk-lib.aws_apigateway.CfnMethod",
                                  "version": "2.122.0"
                                }
                              }
                            },
                            "constructInfo": {
                              "fqn": "aws-cdk-lib.aws_apigateway.Method",
                              "version": "2.122.0"
                            }
                          },
                          "{proxy+}": {
                            "id": "{proxy+}",
                            "path": "costhub-frontend-api-prod/FrontendAPI/Default/api/v1/{proxy+}",
                            "children": {
                              "Resource": {
                                "id": "Resource",
                                "path": "costhub-frontend-api-prod/FrontendAPI/Default/api/v1/{proxy+}/Resource",
                                "attributes": {
                                  "aws:cdk:cloudformation:type": "AWS::ApiGateway::Resource",
                                  "aws:cdk:cloudformation:props": {
                                    "parentId": {
                                      "Ref": "FrontendAPIapiv10C580F49"
                                    },
                                    "pathPart": "{proxy+}",
                                    "restApiId": {
                                      "Ref": "FrontendAPI00E92687"
                                    }
                                  }
                                },
                                "constructInfo": {
                                  "fqn": "aws-cdk-lib.aws_apigateway.CfnResource",
                                  "version": "2.122.0"
                                }
                              },
                              "OPTIONS": {
                                "id": "OPTIONS",
                                "path": "costhub-frontend-api-prod/FrontendAPI/Default/api/v1/{proxy+}/OPTIONS",
                                "children": {
                                  "Resource": {
                                    "id": "Resource",
                                    "path": "costhub-frontend-api-prod/FrontendAPI/Default/api/v1/{proxy+}/OPTIONS/Resource",
                                    "attributes": {
                                      "aws:cdk:cloudformation:type": "AWS::ApiGateway::Method",
                                      "aws:cdk:cloudformation:props": {
                                        "apiKeyRequired": false,
                                        "authorizationType": "NONE",
                                        "httpMethod": "OPTIONS",
                                        "integration": {
                                          "type": "MOCK",
                                          "requestTemplates": {
                                            "application/json": "{ statusCode: 200 }"
                                          },
                                          "integrationResponses": [
                                            {
                                              "statusCode": "204",
                                              "responseParameters": {
                                                "method.response.header.Access-Control-Allow-Headers": "'Content-Type,Authorization,X-Requested-With,x-request-id,X-Amz-Date,X-Api-Key,X-Amz-Security-Token'",
                                                "method.response.header.Access-Control-Allow-Origin": "'https://costhub.4bfast.com.br'",
                                                "method.response.header.Vary": "'Origin'",
                                                "method.response.header.Access-Control-Allow-Methods": "'GET,POST,PUT,DELETE,OPTIONS'",
                                                "method.response.header.Access-Control-Allow-Credentials": "'true'"
                                              },
                                              "responseTemplates": {
                                                "application/json": "#set($origin = $input.params().header.get(\"Origin\"))\n#if($origin == \"\")\n  #set($origin = $input.params().header.get(\"origin\"))\n#end\n#if($origin == \"https://www.costhub.4bfast.com.br\")\n  #set($context.responseOverride.header.Access-Control-Allow-Origin = $origin)\n#end"
                                              }
                                            }
                                          ]
                                        },
                                        "methodResponses": [
                                          {
                                            "statusCode": "204",
                                            "responseParameters": {
                                              "method.response.header.Access-Control-Allow-Headers": true,
                                              "method.response.header.Access-Control-Allow-Origin": true,
                                              "method.response.header.Vary": true,
                                              "method.response.header.Access-Control-Allow-Methods": true,
                                              "method.response.header.Access-Control-Allow-Credentials": true
                                            }
                                          }
                                        ],
                                        "resourceId": {
                                          "Ref": "FrontendAPIapiv1proxy895339E7"
                                        },
                                        "restApiId": {
                                          "Ref": "FrontendAPI00E92687"
                                        }
                                      }
                                    },
                                    "constructInfo": {
                                      "fqn": "aws-cdk-lib.aws_apigateway.CfnMethod",
                                      "version": "2.122.0"
                                    }
                                  }
                                },
                                "constructInfo": {
                                  "fqn": "aws-cdk-lib.aws_apigateway.Method",
                                  "version": "2.122.0"
                                }
                              },
                              "ANY": {
                                "id": "ANY",
                                "path": "costhub-frontend-api-prod/FrontendAPI/Default/api/v1/{proxy+}/ANY",
                                "children": {
                                  "ApiPermission.costhubfrontendapiprodFrontendAPI124EABED.ANY..api.v1.{proxy+}": {
                                    "id": "ApiPermission.costhubfrontendapiprodFrontendAPI124EABED.ANY..api.v1.{proxy+}",
                                    "path": "costhub-frontend-api-prod/FrontendAPI/Default/api/v1/{proxy+}/ANY/ApiPermission.costhubfrontendapiprodFrontendAPI124EABED.ANY..api.v1.{proxy+}",
                                    "attributes": {
                                      "aws:cdk:cloudformation:type": "AWS::Lambda::Permission",
                                      "aws:cdk:cloudformation:props": {
                                        "action": "lambda:InvokeFunction",
                                        "functionName": {
                                          "Fn::GetAtt": [
                                            "APIHandler68F11976",
                                            "Arn"
                                          ]
                                        },
                                        "principal": "apigateway.amazonaws.com",
                                        "sourceArn": {
                                          "Fn::Join": [
                                            "",
                                            [
                                              "arn:",
                                              {
                                                "Ref": "AWS::Partition"
                                              },
                                              ":execute-api:us-east-1:008195334540:",
                                              {
                                                "Ref": "FrontendAPI00E92687"
                                              },
                                              "/",
                                              {
                                                "Ref": "FrontendAPIDeploymentStageprod1F4F1079"
                                              },
                                              "/*/api/v1/*"
                                            ]
                                          ]
                                        }
                                      }
                                    },
                                    "constructInfo": {
                                      "fqn": "aws-cdk-lib.aws_lambda.CfnPermission",
                                      "version": "2.122.0"
                                    }
                                  },
                                  "ApiPermission.Test.costhubfrontendapiprodFrontendAPI124EABED.ANY..api.v1.{proxy+}": {
                                    "id": "ApiPermission.Test.costhubfrontendapiprodFrontendAPI124EABED.ANY..api.v1.{proxy+}",
                                    "path": "costhub-frontend-api-prod/FrontendAPI/Default/api/v1/{proxy+}/ANY/ApiPermission.Test.costhubfrontendapiprodFrontendAPI124EABED.ANY..api.v1.{proxy+}",
                                    "attributes": {
                                      "aws:cdk:cloudformation:type": "AWS::Lambda::Permission",
                                      "aws:cdk:cloudformation:props": {
                                        "action": "lambda:InvokeFunction",
                                        "functionName": {
                                          "Fn::GetAtt": [
                                            "APIHandler68F11976",
                                            "Arn"
                                          ]
                                        },
                                        "principal": "apigateway.amazonaws.com",
                                        "sourceArn": {
                                          "Fn::Join": [
                                            "",
                                            [
                                              "arn:",
                                              {
                                                "Ref": "AWS::Partition"
                                              },
                                              ":execute-api:us-east-1:008195334540:",
                                              {
                                                "Ref": "FrontendAPI00E92687"
                                              },
                                              "/test-invoke-stage/*/api/v1/*"
                                            ]
                                          ]
                                        }
                                      }
                                    },
                                    "constructInfo": {
                                      "fqn": "aws-cdk-lib.aws_lambda.CfnPermission",
                                      "version": "2.122.0"
                                    }
                                  },
                                  "Resource": {
                                    "id": "Resource",
                                    "path": "costhub-frontend-api-prod/FrontendAPI/Default/api/v1/{proxy+}/ANY/Resource",
                                    "attributes": {
                                      "aws:cdk:cloudformation:type": "AWS::ApiGateway::Method",
                                      "aws:cdk:cloudformation:props": {
                                        "authorizationType": "COGNITO_USER_POOLS",
                                        "authorizerId": {
                                          "Ref": "CognitoAuthorizerF3215DBC"
                                        },
                                        "httpMethod": "ANY",
                                        "integration": {
                                          "type": "AWS_PROXY",
                                          "uri": {
                                            "Fn::Join": [
                                              "",
                                              [
                                                "arn:",
                                                {
                                                  "Ref": "AWS::Partition"
                                                },
                                                ":apigateway:us-east-1:lambda:path/2015-03-31/functions/",
                                                {
                                                  "Fn::GetAtt": [
                                                    "APIHandler68F11976",
                                                    "Arn"
                                                  ]
                                                },
                                                "/invocations"
                                              ]
                                            ]
                                          },
                                          "integrationHttpMethod": "POST"
                                        },
                                        "methodResponses": [
                                          {
                                            "statusCode": "200",
                                            "responseParameters": {
                                              "method.response.header.Access-Control-Allow-Origin": true,
                                              "method.response.header.Access-Control-Allow-Headers": true,
                                              "method.response.header.Access-Control-Allow-Methods": true,
                                              "method.response.header.Access-Control-Allow-Credentials": true
                                            }
                                          }
                                        ],
                                        "resourceId": {
                                          "Ref": "FrontendAPIapiv1proxy895339E7"
                                        },
                                        "restApiId": {
                                          "Ref": "FrontendAPI00E92687"
                                        }
                                      }
                                    },
                                    "constructInfo": {
                                      "fqn": "aws-cdk-lib.aws_apigateway.CfnMethod",
                                      "version": "2.122.0"
                                    }
                                  }
                                },
                                "constructInfo": {
                                  "fqn": "aws-cdk-lib.aws_apigateway.Method",
                                  "version": "2.122.0"
                                }
                              }
                            },
                            "constructInfo": {
                              "fqn": "aws-cdk-lib.aws_apigateway.Resource",
                              "version": "2.122.0"
                            }
                          }
                        },
                        "constructInfo": {
                          "fqn": "aws-cdk-lib.aws_apigateway.Resource",
                          "version": "2.122.0"
                        }
                      }
                    },
                    "constructInfo": {
                      "fqn": "aws-cdk-lib.aws_apigateway.Resource",
                      "version": "2.122.0"
                    }
                  }
                },
                "constructInfo": {
                  "fqn": "aws-cdk-lib.aws_apigateway.ResourceBase",
                  "version": "2.122.0"
                }
              }
            },
            "constructInfo": {
              "fqn": "aws-cdk-lib.aws_apigateway.RestApi",
              "version": "2.122.0"
            }
          },
          "Certificate": {
            "id": "Certificate",
            "path": "costhub-frontend-api-prod/Certificate",
            "constructInfo": {
              "fqn": "aws-cdk-lib.Resource",
              "version": "2.122.0"
            }
          },
          "APIDomain": {
            "id": "APIDomain",
            "path": "costhub-frontend-api-prod/APIDomain",
            "children": {
              "Resource": {
                "id": "Resource",
                "path": "costhub-frontend-api-prod/APIDomain/Resource",
                "attributes": {
                  "aws:cdk:cloudformation:type": "AWS::ApiGateway::DomainName",
                  "aws:cdk:cloudformation:props": {
                    "domainName": "api-costhub.4bfast.com.br",
                    "endpointConfiguration": {
                      "types": [
                        "REGIONAL"
                      ]
                    },
                    "regionalCertificateArn": "arn:aws:acm:us-east-1:008195334540:certificate/cc33150f-be90-44d0-87ca-63caf5a48b2f"
                  }
                },
                "constructInfo": {
                  "fqn": "aws-cdk-lib.aws_apigateway.CfnDomainName",
                  "version": "2.122.0"
                }
              },
              "Map:--=>costhubfrontendapiprodFrontendAPI124EABED": {
                "id": "Map:--=>costhubfrontendapiprodFrontendAPI124EABED",
                "path": "costhub-frontend-api-prod/APIDomain/Map:--=>costhubfrontendapiprodFrontendAPI124EABED",
                "children": {
                  "Resource": {
                    "id": "Resource",
                    "path": "costhub-frontend-api-prod/APIDomain/Map:--=>costhubfrontendapiprodFrontendAPI124EABED/Resource",
                    "attributes": {
                      "aws:cdk:cloudformation:type": "AWS::ApiGateway::BasePathMapping",
                      "aws:cdk:cloudformation:props": {
                        "domainName": {
                          "Ref": "APIDomain02CC2FA9"
                        },
                        "restApiId": {
                          "Ref": "FrontendAPI00E92687"
                        },
                        "stage": {
                          "Ref": "FrontendAPIDeploymentStageprod1F4F1079"
                        }
                      }
                    },
                    "constructInfo": {
                      "fqn": "aws-cdk-lib.aws_apigateway.CfnBasePathMapping",
                      "version": "2.122.0"
                    }
                  }
                },
                "constructInfo": {
                  "fqn": "aws-cdk-lib.aws_apigateway.BasePathMapping",
                  "version": "2.122.0"
                }
              }
            },
            "constructInfo": {
              "fqn": "aws-cdk-lib.aws_apigateway.DomainName",
              "version": "2.122.0"
            }
          },
          "HostedZone": {
            "id": "HostedZone",
            "path": "costhub-frontend-api-prod/HostedZone",
            "constructInfo": {
              "fqn": "aws-cdk-lib.Resource",
              "version": "2.122.0"
            }
          },
          "APIAliasRecord": {
            "id": "APIAliasRecord",
            "path": "costhub-frontend-api-prod/APIAliasRecord",
            "children": {
              "Resource": {
                "id": "Resource",
                "path": "costhub-frontend-api-prod/APIAliasRecord/Resource",
                "attributes": {
                  "aws:cdk:cloudformation:type": "AWS::Route53::RecordSet",
                  "aws:cdk:cloudformation:props": {
                    "aliasTarget": {
                      "dnsName": {
                        "Fn::GetAtt": [
                          "APIDomain02CC2FA9",
                          "RegionalDomainName"
                        ]
                      },
                      "hostedZoneId": {
                        "Fn::GetAtt": [
                          "APIDomain02CC2FA9",
                          "RegionalHostedZoneId"
                        ]
                      }
                    },
                    "hostedZoneId": "Z05900913NMLNYFKQHMUL",
                    "name": "api-costhub.4bfast.com.br.",
                    "type": "A"
                  }
                },
                "constructInfo": {
                  "fqn": "aws-cdk-lib.aws_route53.CfnRecordSet",
                  "version": "2.122.0"
                }
              }
            },
            "constructInfo": {
              "fqn": "aws-cdk-lib.aws_route53.ARecord",
              "version": "2.122.0"
            }
          },
          "FrontendAPIUrl": {
            "id": "FrontendAPIUrl",
            "path": "costhub-frontend-api-prod/FrontendAPIUrl",
            "constructInfo": {
              "fqn": "aws-cdk-lib.CfnOutput",
              "version": "2.122.0"
            }
          },
          "CustomDomainUrl": {
            "id": "CustomDomainUrl",
            "path": "costhub-frontend-api-prod/CustomDomainUrl",
            "constructInfo": {
              "fqn": "aws-cdk-lib.CfnOutput",
              "version": "2.122.0"
            }
          },
          "FrontendAPIId": {
            "id": "FrontendAPIId",
            "path": "costhub-frontend-api-prod/FrontendAPIId",
            "constructInfo": {
              "fqn": "aws-cdk-lib.CfnOutput",
              "version": "2.122.0"
            }
          },
          "CDKMetadata": {
            "id": "CDKMetadata",
            "path": "costhub-frontend-api-prod/CDKMetadata",
            "children": {
              "Default": {
                "id": "Default",
                "path": "costhub-frontend-api-prod/CDKMetadata/Default",
                "constructInfo": {
                  "fqn": "aws-cdk-lib.CfnResource",
                  "version": "2.122.0"
                }
              }
            },
            "constructInfo": {
              "fqn": "constructs.Construct",
              "version": "10.4.2"
            }
          },
          "BootstrapVersion": {
            "id": "BootstrapVersion",
            "path": "costhub-frontend-api-prod/BootstrapVersion",
            "constructInfo": {
              "fqn": "aws-cdk-lib.CfnParameter",
              "version": "2.122.0"
            }
          },
          "CheckBootstrapVersion": {
            "id": "CheckBootstrapVersion",
            "path": "costhub-frontend-api-prod/CheckBootstrapVersion",
            "constructInfo": {
              "fqn": "aws-cdk-lib.CfnRule",
              "version": "2.122.0"
            }
          }
        },
        "constructInfo": {
          "fqn": "aws-cdk-lib.Stack",
          "version": "2.122.0"
        }
      },
      "costhub-frontend-prod": {
        "id": "costhub-frontend-prod",
        "path": "costhub-frontend-prod",
        "children": {
          "FrontendBucket": {
            "id": "FrontendBucket",
            "path": "costhub-frontend-prod/FrontendBucket",
            "children": {
              "Resource": {
                "id": "Resource",
                "path": "costhub-frontend-prod/FrontendBucket/Resource",
                "attributes": {
                  "aws:cdk:cloudformation:type": "AWS::S3::Bucket",
                  "aws:cdk:cloudformation:props": {
                    "bucketName": "costhub-frontend-4bfast",
                    "publicAccessBlockConfiguration": {
                      "blockPublicAcls": false,
                      "blockPublicPolicy": false,
                      "ignorePublicAcls": false,
                      "restrictPublicBuckets": false
                    },
                    "tags": [
                      {
                        "key": "aws-cdk:auto-delete-objects",
                        "value": "true"
                      }
                    ],
                    "websiteConfiguration": {
                      "indexDocument": "index.html",
                      "errorDocument": "index.html"
                    }
                  }
                },
                "constructInfo": {
                  "fqn": "aws-cdk-lib.aws_s3.CfnBucket",
                  "version": "2.122.0"
                }
              },
              "Policy": {
                "id": "Policy",
                "path": "costhub-frontend-prod/FrontendBucket/Policy",
                "children": {
                  "Resource": {
                    "id": "Resource",
                    "path": "costhub-frontend-prod/FrontendBucket/Policy/Resource",
                    "attributes": {
                      "aws:cdk:cloudformation:type": "AWS::S3::BucketPolicy",
                      "aws:cdk:cloudformation:props": {
                        "bucket": {
                          "Ref": "FrontendBucketEFE2E19C"
                        },
                        "policyDocument": {
                          "Statement": [
                            {
                              "Action": "s3:GetObject",
                              "Effect": "Allow",
                              "Principal": {
                                "AWS": "*"
                              },
                              "Resource": {
                                "Fn::Join": [
                                  "",
                                  [
                                    {
                                      "Fn::GetAtt": [
                                        "FrontendBucketEFE2E19C",
                                        "Arn"
                                      ]
                                    },
                                    "/*"
                                  ]
                                ]
                              }
                            },
                            {
                              "Action": [
                                "s3:PutBucketPolicy",
                                "s3:GetBucket*",
                                "s3:List*",
                                "s3:DeleteObject*"
                              ],
                              "Effect": "Allow",
                              "Principal": {
                                "AWS": {
                                  "Fn::GetAtt": [
                                    "CustomS3AutoDeleteObjectsCustomResourceProviderRole3B1BD092",
                                    "Arn"
                                  ]
                                }
                              },
                              "Resource": [
                                {
                                  "Fn::GetAtt": [
                                    "FrontendBucketEFE2E19C",
                                    "Arn"
                                  ]
                                },
                                {
                                  "Fn::Join": [
                                    "",
                                    [
                                      {
                                        "Fn::GetAtt": [
                                          "FrontendBucketEFE2E19C",
                                          "Arn"
                                        ]
                                      },
                                      "/*"
                                    ]
                                  ]
                                }
                              ]
                            }
                          ],
                          "Version": "2012-10-17"
                        }
                      }
                    },
                    "constructInfo": {
                      "fqn": "aws-cdk-lib.aws_s3.CfnBucketPolicy",
                      "version": "2.122.0"
                    }
                  }
                },
                "constructInfo": {
                  "fqn": "aws-cdk-lib.aws_s3.BucketPolicy",
                  "version": "2.122.0"
                }
              },
              "AutoDeleteObjectsCustomResource": {
                "id": "AutoDeleteObjectsCustomResource",
                "path": "costhub-frontend-prod/FrontendBucket/AutoDeleteObjectsCustomResource",
                "children": {
                  "Default": {
                    "id": "Default",
                    "path": "costhub-frontend-prod/FrontendBucket/AutoDeleteObjectsCustomResource/Default",
                    "constructInfo": {
                      "fqn": "aws-cdk-lib.CfnResource",
                      "version": "2.122.0"
                    }
                  }
                },
                "constructInfo": {
                  "fqn": "aws-cdk-lib.CustomResource",
                  "version": "2.122.0"
                }
              }
            },
            "constructInfo": {
              "fqn": "aws-cdk-lib.aws_s3.Bucket",
              "version": "2.122.0"
            }
          },
          "Custom::S3AutoDeleteObjectsCustomResourceProvider": {
            "id": "Custom::S3AutoDeleteObjectsCustomResourceProvider",
            "path": "costhub-frontend-prod/Custom::S3AutoDeleteObjectsCustomResourceProvider",
            "children": {
              "Staging": {
                "id": "Staging",
                "path": "costhub-frontend-prod/Custom::S3AutoDeleteObjectsCustomResourceProvider/Staging",
                "constructInfo": {
                  "fqn": "aws-cdk-lib.AssetStaging",
                  "version": "2.122.0"
                }
              },
              "Role": {
                "id": "Role",
                "path": "costhub-frontend-prod/Custom::S3AutoDeleteObjectsCustomResourceProvider/Role",
                "constructInfo": {
                  "fqn": "aws-cdk-lib.CfnResource",
                  "version": "2.122.0"
                }
              },
              "Handler": {
                "id": "Handler",
                "path": "costhub-frontend-prod/Custom::S3AutoDeleteObjectsCustomResourceProvider/Handler",
                "constructInfo": {
                  "fqn": "aws-cdk-lib.CfnResource",
                  "version": "2.122.0"
                }
              }
            },
            "constructInfo": {
              "fqn": "aws-cdk-lib.CustomResourceProviderBase",
              "version": "2.122.0"
            }
          },
          "Certificate": {
            "id": "Certificate",
            "path": "costhub-frontend-prod/Certificate",
            "constructInfo": {
              "fqn": "aws-cdk-lib.Resource",
              "version": "2.122.0"
            }
          },
          "FrontendDistribution": {
            "id": "FrontendDistribution",
            "path": "costhub-frontend-prod/FrontendDistribution",
            "children": {
              "Origin1": {
                "id": "Origin1",
                "path": "costhub-frontend-prod/FrontendDistribution/Origin1",
                "constructInfo": {
                  "fqn": "constructs.Construct",
                  "version": "10.4.2"
                }
              },
              "Resource": {
                "id": "Resource",
                "path": "costhub-frontend-prod/FrontendDistribution/Resource",
                "attributes": {
                  "aws:cdk:cloudformation:type": "AWS::CloudFront::Distribution",
                  "aws:cdk:cloudformation:props": {
                    "distributionConfig": {
                      "enabled": true,
                      "origins": [
                        {
                          "domainName": {
                            "Fn::Select": [
                              2,
                              {
                                "Fn::Split": [
                                  "/",
                                  {
                                    "Fn::GetAtt": [
                                      "FrontendBucketEFE2E19C",
                                      "WebsiteURL"
                                    ]
                                  }
                                ]
                              }
                            ]
                          },
                          "id": "costhubfrontendprodFrontendDistributionOrigin118E59301",
                          "customOriginConfig": {
                            "originSslProtocols": [
                              "TLSv1.2"
                            ],
                            "originProtocolPolicy": "http-only"
                          }
                        }
                      ],
                      "defaultCacheBehavior": {
                        "pathPattern": "*",
                        "targetOriginId": "costhubfrontendprodFrontendDistributionOrigin118E59301",
                        "allowedMethods": [
                          "GET",
                          "HEAD",
                          "OPTIONS"
                        ],
                        "cachePolicyId": "658327ea-f89d-4fab-a63d-7e88639e58f6",
                        "compress": true,
                        "viewerProtocolPolicy": "redirect-to-https"
                      },
                      "aliases": [
                        "costhub.4bfast.com.br"
                      ],
                      "customErrorResponses": [
                        {
                          "errorCode": 404,
                          "responseCode": 200,
                          "responsePagePath": "/index.html"
                        },
                        {
                          "errorCode": 403,
                          "responseCode": 200,
                          "responsePagePath": "/index.html"
                        }
                      ],
                      "defaultRootObject": "index.html",
                      "httpVersion": "http2",
                      "ipv6Enabled": true,
                      "priceClass": "PriceClass_100",
                      "viewerCertificate": {
                        "acmCertificateArn": "arn:aws:acm:us-east-1:008195334540:certificate/cc33150f-be90-44d0-87ca-63caf5a48b2f",
                        "minimumProtocolVersion": "TLSv1.2_2021",
                        "sslSupportMethod": "sni-only"
                      }
                    }
                  }
                },
                "constructInfo": {
                  "fqn": "aws-cdk-lib.aws_cloudfront.CfnDistribution",
                  "version": "2.122.0"
                }
              }
            },
            "constructInfo": {
              "fqn": "aws-cdk-lib.aws_cloudfront.Distribution",
              "version": "2.122.0"
            }
          },
          "BucketName": {
            "id": "BucketName",
            "path": "costhub-frontend-prod/BucketName",
            "constructInfo": {
              "fqn": "aws-cdk-lib.CfnOutput",
              "version": "2.122.0"
            }
          },
          "DistributionId": {
            "id": "DistributionId",
            "path": "costhub-frontend-prod/DistributionId",
            "constructInfo": {
              "fqn": "aws-cdk-lib.CfnOutput",
              "version": "2.122.0"
            }
          },
          "DistributionDomainName": {
            "id": "DistributionDomainName",
            "path": "costhub-frontend-prod/DistributionDomainName",
            "constructInfo": {
              "fqn": "aws-cdk-lib.CfnOutput",
              "version": "2.122.0"
            }
          },
          "WebsiteUrl": {
            "id": "WebsiteUrl",
            "path": "costhub-frontend-prod/WebsiteUrl",
            "constructInfo": {
              "fqn": "aws-cdk-lib.CfnOutput",
              "version": "2.122.0"
            }
          },
          "CloudflareCNAME": {
            "id": "CloudflareCNAME",
            "path": "costhub-frontend-prod/CloudflareCNAME",
            "constructInfo": {
              "fqn": "aws-cdk-lib.CfnOutput",
              "version": "2.122.0"
            }
          },
          "CDKMetadata": {
            "id": "CDKMetadata",
            "path": "costhub-frontend-prod/CDKMetadata",
            "children": {
              "Default": {
                "id": "Default",
                "path": "costhub-frontend-prod/CDKMetadata/Default",
                "constructInfo": {
                  "fqn": "aws-cdk-lib.CfnResource",
                  "version": "2.122.0"
                }
              }
            },
            "constructInfo": {
              "fqn": "constructs.Construct",
              "version": "10.4.2"
            }
          },
          "BootstrapVersion": {
            "id": "BootstrapVersion",
            "path": "costhub-frontend-prod/BootstrapVersion",
            "constructInfo": {
              "fqn": "aws-cdk-lib.CfnParameter",
              "version": "2.122.0"
            }
          },
          "CheckBootstrapVersion": {
            "id": "CheckBootstrapVersion",
            "path": "costhub-frontend-prod/CheckBootstrapVersion",
            "constructInfo": {
              "fqn": "aws-cdk-lib.CfnRule",
              "version": "2.122.0"
            }
          }
        },
        "constructInfo": {
          "fqn": "aws-cdk-lib.Stack",
          "version": "2.122.0"
        }
      },
      "Tree": {
        "id": "Tree",
        "path": "Tree",
        "constructInfo": {
          "fqn": "constructs.Construct",
          "version": "10.4.2"
        }
      }
    },
    "constructInfo": {
      "fqn": "aws-cdk-lib.App",
      "version": "2.122.0"
    }
  }
}